executor_plus/__init__.py
executor_plus/__version__.py
executor_plus/utils.py
executor_plus/addons/__init__.py
executor_plus/addons/progress.py
executor_plus/addons/throttle.py
executor_plus/addons/worker_id.py
executor_plus/futures/__init__.py
executor_plus/futures/addon.py
executor_plus/futures/basic_immediate_executor.py
executor_plus/futures/executors.py
executor_plus/futures/start_all_workers.py
executor_plus-1.0.0.dist-info/LICENSE
executor_plus-1.0.0.dist-info/METADATA
executor_plus-1.0.0.dist-info/WHEEL
executor_plus-1.0.0.dist-info/top_level.txt
executor_plus-1.0.0.dist-info/RECORD
