Metadata-Version: 2.1
Name: executor_plus
Version: 1.0.0
Summary: An advanced executor library for Python with progress tracking, throttling, and more.
Home-page: https://github.com/yourusername/executor_plus
Author: Yuting Zhang
Author-email: opensource@yuting.link
Classifier: Programming Language :: Python :: 3
Classifier: License :: OSI Approved :: GNU Lesser General Public License v2 (LGPLv2)
Classifier: Operating System :: OS Independent
Requires-Python: >=3.8
License-File: LICENSE
